tagops/__init__.py
tagops/main.py
tagops/setup.py
tagops/tagops.py
tagops/core/__init__.py
tagops/core/aws.py
tagops/core/context.py
tagops/core/executor.py
tagops/core/planner.py
tagops/core/resource.py
tagops/core/ui.py
tagops/services/__init__.py
tagops/services/asg/__init__.py
tagops/services/asg/actions.py
tagops/services/asg/discover.py
tagops/services/asg/enrich.py
tagops/services/ec2/__init__.py
tagops/services/ec2/actions.py
tagops/services/ec2/discover.py
tagops/services/ec2/enrich.py
tagops/services/ec2/plan.py
tagops/utils/__init__.py
tagops/utils/format.py
tagops/utils/waiter.py
tagops-0.1.1.dist-info/licenses/LICENSE
tagops-0.1.1.dist-info/METADATA
tagops-0.1.1.dist-info/WHEEL
tagops-0.1.1.dist-info/entry_points.txt
tagops-0.1.1.dist-info/top_level.txt
tagops-0.1.1.dist-info/RECORD
